ezclient.cpython-37m-darwin.so
Ezclient.dylibs/libezclient.so
Ezclient-1.2.0.dist-info/RECORD
Ezclient-1.2.0.dist-info/LICENSE
Ezclient-1.2.0.dist-info/WHEEL
Ezclient-1.2.0.dist-info/top_level.txt
Ezclient-1.2.0.dist-info/METADATA
