Metadata-Version: 2.1
Name: Ezclient
Version: 1.2.0
Summary: P2P client library
Author: Riccardo Viviano, Matteo Galdi
Author-email: riccardoviviano@gmail.com
License-File: LICENSE
